{
  "metals": [
    {
      "name": "Gram Altın",
      "code": "Gram",
      "price": "6249.03",
      "change": 0.02
    },
    {
      "name": "Kapalı Çarşı Gram Altın",
      "code": "Fiziki",
      "price": "6387.62",
      "change": 0.03
    },
    {
      "name": "Çeyrek Altın",
      "code": "Çeyrek",
      "price": "10446.97",
      "change": -0.01
    },
    {
      "name": "Ons Altın",
      "code": "Ons/USD",
      "price": "195216.98",
      "change": 0.015
    },
    {
      "name": "Gümüş Gram",
      "code": "Gümüş",
      "price": "101.22",
      "change": 0.005
    },
    {
      "name": "Platin Gram",
      "code": "Platin",
      "price": "2562.00",
      "change": -0.008
    }
  ],
  "banks": [
    {
      "name": "Garanti BBVA",
      "buy": "6157.70",
      "sell": "6588.60",
      "change": 0.025
    },
    {
      "name": "Akbank",
      "buy": "6108.58",
      "sell": "6651.83",
      "change": 0.032
    },
    {
      "name": "Yapı Kredi",
      "buy": "6122.91",
      "sell": "6574.76",
      "change": 0.018
    }
  ],
  "last_updated": "2026-06-13T20:03:49.122959+00:00"
}